troubleshoot_mcp_server/__init__.py
troubleshoot_mcp_server/__main__.py
troubleshoot_mcp_server/bundle.py
troubleshoot_mcp_server/cli.py
troubleshoot_mcp_server/config.py
troubleshoot_mcp_server/files.py
troubleshoot_mcp_server/formatters.py
troubleshoot_mcp_server/kubectl.py
troubleshoot_mcp_server/lifecycle.py
troubleshoot_mcp_server/py.typed
troubleshoot_mcp_server/server.py
troubleshoot_mcp_server/size_limiter.py
troubleshoot_mcp_server/subprocess_utils.py
troubleshoot_mcp_server-1.15.1.dist-info/licenses/LICENSE
troubleshoot_mcp_server-1.15.1.dist-info/METADATA
troubleshoot_mcp_server-1.15.1.dist-info/WHEEL
troubleshoot_mcp_server-1.15.1.dist-info/entry_points.txt
troubleshoot_mcp_server-1.15.1.dist-info/top_level.txt
troubleshoot_mcp_server-1.15.1.dist-info/RECORD
