Metadata-Version: 2.4
Name: troubleshoot-mcp-server
Version: 1.15.1
Summary: MCP server for Kubernetes support bundles
Author-email: Chris Nesbitt-Smith <chris@cns.me>
License-Expression: Apache-2.0
Project-URL: Homepage, https://github.com/chrisns/troubleshoot-mcp-server
Project-URL: Repository, https://github.com/chrisns/troubleshoot-mcp-server
Project-URL: Issues, https://github.com/chrisns/troubleshoot-mcp-server/issues
Keywords: mcp,kubernetes,troubleshoot,support-bundle,ai,claude,debugging
Classifier: Programming Language :: Python :: 3
Classifier: Programming Language :: Python :: 3.13
Classifier: Operating System :: OS Independent
Classifier: Development Status :: 3 - Alpha
Classifier: Intended Audience :: Developers
Classifier: Intended Audience :: System Administrators
Classifier: Topic :: Software Development :: Libraries :: Python Modules
Classifier: Topic :: System :: Systems Administration
Requires-Python: >=3.13
License-File: LICENSE
Requires-Dist: mcp
Requires-Dist: pydantic
Requires-Dist: aiohttp
Requires-Dist: fastapi
Requires-Dist: uvicorn
Requires-Dist: typer
Requires-Dist: pyyaml
Requires-Dist: psutil
Provides-Extra: dev
Requires-Dist: pytest; extra == "dev"
Requires-Dist: pytest-asyncio; extra == "dev"
Requires-Dist: pytest-timeout; extra == "dev"
Requires-Dist: pytest-cov; extra == "dev"
Requires-Dist: ruff; extra == "dev"
Requires-Dist: mypy; extra == "dev"
Requires-Dist: types-PyYAML; extra == "dev"
Dynamic: license-file
